ticketbookinglib/__init__.py
ticketbookinglib/bookingalert.py
ticketbookinglib-0.0.6.dist-info/LICENCE
ticketbookinglib-0.0.6.dist-info/METADATA
ticketbookinglib-0.0.6.dist-info/WHEEL
ticketbookinglib-0.0.6.dist-info/top_level.txt
ticketbookinglib-0.0.6.dist-info/RECORD
