Metadata-Version: 2.1
Name: ticketbookinglib
Version: 0.0.6
Summary: This is a simple booking notification alert shown for booking confirmation.
Home-page: 
Author: Syam Sundar Reddy Maddula 
Author-email: x23307862@student.ncirl.ie
License: MIT
Keywords: ticketbookinglib
Classifier: Development Status :: 5 - Production/Stable
Classifier: Intended Audience :: Education
Classifier: Operating System :: Microsoft :: Windows :: Windows 10
Classifier: License :: OSI Approved :: MIT License
Classifier: Programming Language :: Python :: 3
Requires-Python: >=3.6
License-File: LICENCE
